{
  "fetched_at": "2026-02-25T16:18:57+00:00",
  "source": "https://finance.naver.com/marketindex/exchangeList.naver",
  "build_sha": "bd72ad5",
  "rates_by_type": {
    "sale": {
      "KRW": 1.0,
      "USD": 1427.6,
      "CNY": 208.26,
      "PHP": 24.81,
      "TWD": 45.58,
      "JPY": 9.1267,
      "VND": 0.0548,
      "THB": 45.96,
      "EUR": 1685.28,
      "AUD": 1015.38
    },
    "buy": {
      "KRW": 1.0,
      "USD": 1452.58,
      "CNY": 218.67,
      "PHP": 27.29,
      "TWD": 51.55,
      "JPY": 9.2864,
      "VND": 0.061200000000000004,
      "THB": 48.25,
      "EUR": 1718.81,
      "AUD": 1035.38
    },
    "sell": {
      "KRW": 1.0,
      "USD": 1402.62,
      "CNY": 197.85,
      "PHP": 22.78,
      "TWD": 41.03,
      "JPY": 8.967,
      "VND": 0.0484,
      "THB": 43.21,
      "EUR": 1651.75,
      "AUD": 995.38
    },
    "send": {
      "KRW": 1.0,
      "USD": 1441.5,
      "CNY": 210.34,
      "PHP": 25.05,
      "TWD": 46.08,
      "JPY": 9.2161,
      "VND": 0.0553,
      "THB": 46.41,
      "EUR": 1702.13,
      "AUD": 1025.53
    },
    "receive": {
      "KRW": 1.0,
      "USD": 1413.7,
      "CNY": 206.18,
      "PHP": 24.57,
      "TWD": 45.08,
      "JPY": 9.0373,
      "VND": 0.054299999999999994,
      "THB": 45.51,
      "EUR": 1668.43,
      "AUD": 1005.23
    }
  },
  "currencies": [
    {
      "code": "KRW",
      "label": "Korean Won (KRW)",
      "source_unit": 1
    },
    {
      "code": "USD",
      "label": "US Dollar (USD)",
      "source_unit": 1
    },
    {
      "code": "CNY",
      "label": "Chinese Yuan (CNY)",
      "source_unit": 1
    },
    {
      "code": "PHP",
      "label": "Philippine Peso (PHP)",
      "source_unit": 1
    },
    {
      "code": "TWD",
      "label": "Taiwan Dollar (TWD)",
      "source_unit": 1
    },
    {
      "code": "JPY",
      "label": "Japanese Yen (JPY)",
      "source_unit": 100
    },
    {
      "code": "VND",
      "label": "Vietnamese Dong (VND)",
      "source_unit": 100
    },
    {
      "code": "THB",
      "label": "Thai Baht (THB)",
      "source_unit": 1
    },
    {
      "code": "EUR",
      "label": "Euro (EUR)",
      "source_unit": 1
    },
    {
      "code": "AUD",
      "label": "Australian Dollar (AUD)",
      "source_unit": 1
    }
  ]
}